psghotkey/LICENSE.txt
psghotkey/README.md
psghotkey/__init__.py
psghotkey/__main__.py
psghotkey/psghotkey.py
psghotkey/screenshot.gif
psghotkey/screenshot.jpg
psghotkey-5.0.0.dist-info/LICENSE.txt
psghotkey-5.0.0.dist-info/METADATA
psghotkey-5.0.0.dist-info/WHEEL
psghotkey-5.0.0.dist-info/entry_points.txt
psghotkey-5.0.0.dist-info/top_level.txt
psghotkey-5.0.0.dist-info/RECORD
